knowledge_engineer/AI_API_Costs.py
knowledge_engineer/__init__.py
knowledge_engineer/ai.py
knowledge_engineer/create_new_process.py
knowledge_engineer/db.py
knowledge_engineer/ke.py
knowledge_engineer/line_statement.py
knowledge_engineer/logger.py
knowledge_engineer/step.py
knowledge_engineer/version.py
knowledge_engineer-0.7.5.dist-info/LICENSE
knowledge_engineer-0.7.5.dist-info/METADATA
knowledge_engineer-0.7.5.dist-info/WHEEL
knowledge_engineer-0.7.5.dist-info/entry_points.txt
knowledge_engineer-0.7.5.dist-info/top_level.txt
knowledge_engineer-0.7.5.dist-info/RECORD
