Metadata-Version: 2.1
Name: knowledge_engineer
Version: 0.7.5
Summary: Engineer GPT Knowledge within a project
Author-email: Jerry Westrick <jerry@westrick.com>
Classifier: Programming Language :: Python :: 3
Classifier: License :: OSI Approved :: MIT License
Classifier: Operating System :: OS Independent
Requires-Python: >=3.10
License-File: LICENSE
Requires-Dist: aioconsole
Requires-Dist: aiohttp
Requires-Dist: ansi2html
Requires-Dist: anthropic
Requires-Dist: asyncio
Requires-Dist: databases
Requires-Dist: groq
Requires-Dist: knowledge-engineer
Requires-Dist: lark
Requires-Dist: mistralai
Requires-Dist: openai
Requires-Dist: prompt-toolkit
Requires-Dist: python-dotenv
Requires-Dist: rich
